sake/__init__.py
sake/_version.py
sake/flows.py
sake/functional.py
sake/layers.py
sake/models.py
sake/utils.py
sake_gnn-0.0.2.post1.dist-info/LICENSE
sake_gnn-0.0.2.post1.dist-info/METADATA
sake_gnn-0.0.2.post1.dist-info/WHEEL
sake_gnn-0.0.2.post1.dist-info/top_level.txt
sake_gnn-0.0.2.post1.dist-info/RECORD
