Metadata-Version: 2.1
Name: sake-gnn
Version: 0.0.2.post1
Summary: UNKNOWN
Author: Yuanqing Wang
Author-email: wangyq@wangyq.net
License: MIT
Platform: UNKNOWN
License-File: LICENSE
Requires-Dist: jax
Requires-Dist: jaxlib
